<?xml version="1.0" encoding="UTF-8"?>

<ValueSet xmlns="http://hl7.org/fhir">
  <id value="JDV-J80Abdelali-Sexe-RASS-all"/>
  <meta>
    <versionId value="1"/>
    <lastUpdated value="2022-09-22T08:46:28.440+00:00"/>
  </meta>
  <text>
    <status value="generated"/><div xmlns="http://www.w3.org/1999/xhtml">Placeholder</div>
  </text>
  <extension url="http://hl7.org/fhir/StructureDefinition/ressource-effectivePeriod">
    <valuePeriod>
      <start value="2019-08-30T12:00:00+01:00"/>
    </valuePeriod>
  </extension>
  <url value="https://mos.esante.gouv.fr/NOS/JDV_J80-Sexe-RASS/FHIR/JDV-J80Abdelali-Sexe-RASS-all"/>
  <identifier>
    <value value="urn:oid:1.2.250.1.213.1.6.1.148"/>
  </identifier>
  <version value="1.1.0"/>
  <name value="JDV-J80Abdelali-Sexe-RASS-all"/>
  <status value="active"/>
  <date value="2020-04-24T12:00:00+01:00"/>
  <publisher value="ANS"/>
  <contact>
    <name value="ANS"/>
    <telecom>
      <system value="url"/>
      <value value="https://esante.gouv.fr"/>
    </telecom>
  </contact>
  <description value="Sexe des professionnels du RASS"/>
  <compose>
    <include>
      <system value="https://mos.esante.gouv.fr/NOS/TRE_R249-Sexe/FHIR/TRE-R249-Sexe"/>
    </include>
  </compose>
</ValueSet>